gitlab3
