Metadata-Version: 1.0
Name: gitlab3
Version: 0.5.2
Summary: GitLab API v3 Python Wrapper.
Home-page: http://github.com/alexvh/python-gitlab3
Author: Alex Van't Hof
Author-email: alexvh@cs.columbia.edu
License: LGPLv3
Keywords: gitlab api client wrapper
Platform: UNKNOWN
